code_monger/__init__.py
code_monger/code_generator.py
code_monger/intro.py
code_monger-0.1.9.dist-info/licenses/LICENSE.txt
code_monger-0.1.9.dist-info/METADATA
code_monger-0.1.9.dist-info/WHEEL
code_monger-0.1.9.dist-info/top_level.txt
code_monger-0.1.9.dist-info/RECORD
